bas_convert/__init__.py
bas_convert/__main__.py
bas_convert/convert.py
bas_convert/data/lookups.json
bas_convert-0.0.1.dist-info/METADATA
bas_convert-0.0.1.dist-info/WHEEL
bas_convert-0.0.1.dist-info/entry_points.txt
bas_convert-0.0.1.dist-info/top_level.txt
bas_convert-0.0.1.dist-info/RECORD
